espejo/__init__.py
espejo/compare.py
espejo/config.py
espejo/errors.py
espejo/ignore.py
espejo-0.1.2.dist-info/LICENSE.txt
espejo-0.1.2.dist-info/METADATA
espejo-0.1.2.dist-info/WHEEL
espejo-0.1.2.dist-info/RECORD
