Metadata-Version: 2.1
Name: espejo
Version: 0.1.2
Summary: a compare utility
Home-page: https://pypi.org/project/espejo
License: MIT
Keywords: json,compare
Author: Gleb Karpushkin
Author-email: rugleb@gmail.com
Maintainer: Jorge Gueorguiev Garcia
Maintainer-email: jorge.gueorguiev@twoormore.eu
Requires-Python: >=3.9,<4.0
Classifier: License :: OSI Approved :: MIT License
Classifier: Operating System :: OS Independent
Classifier: Programming Language :: Python :: 3
Classifier: Programming Language :: Python :: 3.9
Classifier: Programming Language :: Python :: 3.10
Classifier: Programming Language :: Python :: 3.11
Classifier: Topic :: Software Development :: Libraries
Classifier: Topic :: Software Development :: Testing
Project-URL: Documentation, https://github.com/twoormore/espejo/blob/master/README.md
Project-URL: Repository, https://github.com/twoormore/espejo
